sportsrefapi/__init__.py
sportsrefapi/nba/__init__.py
sportsrefapi/nba/columns.py
sportsrefapi/nba/gamelogs.py
sportsrefapi/nba/players.py
sportsrefapi-0.1.2.dist-info/METADATA
sportsrefapi-0.1.2.dist-info/WHEEL
sportsrefapi-0.1.2.dist-info/top_level.txt
sportsrefapi-0.1.2.dist-info/RECORD
