Metadata-Version: 2.1
Name: sportsrefapi
Version: 0.1.2
Summary: Python package for parsing stats from sports reference.
Home-page: https://gitlab.com/mefortunato/sports-reference
Author: Mike Fortunato
Author-email: mike@mfort.dev
License: UNKNOWN
Project-URL: Bug Tracker, https://gitlab.com/mefortunato/sports-reference/-/issues
Platform: UNKNOWN
Classifier: Programming Language :: Python :: 3
Classifier: License :: OSI Approved :: MIT License
Classifier: Operating System :: OS Independent
Requires-Python: >=3.6
Requires-Dist: bs4
Requires-Dist: html5lib
Requires-Dist: httpx
Requires-Dist: lxml
Requires-Dist: numpy
Requires-Dist: pandas
